usagi-0.3.1.dist-info/top_level.txt
usagi-0.3.1.dist-info/entry_points.txt
usagi-0.3.1.dist-info/WHEEL
usagi-0.3.1.dist-info/DESCRIPTION.rst
usagi-0.3.1.dist-info/METADATA
usagi-0.3.1.dist-info/RECORD
usagi-0.3.1.dist-info/pbr.json
usagi-0.3.1.dist-info/metadata.json
usagi/parameter_builder.py
usagi/var_loader.py
usagi/config.py
usagi/yaml_test_loader.py
usagi/_version.py
usagi/utils.py
usagi/schema.py
usagi/web_test.py
usagi/exceptions.py
usagi/discoverer.py
usagi/__init__.py
usagi/plugins/i_test_parameter.py
usagi/plugins/i_assertion.py
usagi/plugins/assertions.py
usagi/plugins/i_var_loader.py
usagi/plugins/var_loaders.py
usagi/plugins/__init__.py
usagi/plugins/test_parameters.py
