Metadata-Version: 2.0
Name: usagi
Version: 0.3.1
Summary: Web API testing for haas
Home-page: https://github.com/sjagoe/usagi
Author: Simon Jagoe
Author-email: simon@simonjagoe.com
License: BSD
Platform: UNKNOWN
Classifier: Development Status :: 1 - Planning
Classifier: Intended Audience :: Developers
Classifier: License :: OSI Approved :: BSD License
Classifier: Operating System :: MacOS
Classifier: Operating System :: Microsoft :: Windows
Classifier: Operating System :: OS Independent
Classifier: Operating System :: POSIX
Classifier: Operating System :: Unix
Classifier: Programming Language :: Python
Classifier: Topic :: Software Development
Classifier: Topic :: Software Development :: Testing
Requires-Dist: jsonschema
Requires-Dist: pyyaml
Requires-Dist: requests
Requires-Dist: six
Requires-Dist: stevedore
Requires-Dist: haas (>=0.6.0)
Requires-Dist: jq (>=0.1.3,<0.2)
Requires-Dist: unittest2; python_version=="2.6"
